cantoogf/__init__.py
cantoogf/foo.py
cantoogf-1.0.9.dist-info/WHEEL
cantoogf-1.0.9.dist-info/METADATA
cantoogf-1.0.9.dist-info/RECORD
