Metadata-Version: 2.1
Name: cantoogf
Version: 1.0.9
Summary: An amazing sample package!
Author-email: Laika Dog <laika@woof.com>
